{
  "meta": {
    "version": "1.0.0",
    "generatedAt": "2026-07-22T14:28:14.075Z",
    "sourcesResolved": 3,
    "sourcesTotal": 6
  },
  "layers": {
    "seismic": {
      "count": 17,
      "maxMagnitude": 7.5,
      "events": [
        {
          "id": "us7000t1q7",
          "magnitude": 5.5,
          "place": "4 km SSW of Chupaca, Peru",
          "time": "2026-07-19T02:24:35.623Z",
          "coordinates": [
            -75.3034,
            -12.1036,
            10
          ],
          "tsunami": false,
          "significance": 658
        },
        {
          "id": "us7000t1cc",
          "magnitude": 6.4,
          "place": "86 km WSW of Puerto Madero, Mexico",
          "time": "2026-07-17T15:20:07.228Z",
          "coordinates": [
            -93.1039,
            14.308,
            10
          ],
          "tsunami": false,
          "significance": 631
        },
        {
          "id": "us7000t1bu",
          "magnitude": 7.3,
          "place": "58 km WSW of Puerto Madero, Mexico",
          "time": "2026-07-17T14:48:39.769Z",
          "coordinates": [
            -92.9517,
            14.6043,
            18.584
          ],
          "tsunami": false,
          "significance": 974
        },
        {
          "id": "us7000t0d0",
          "magnitude": 6.2,
          "place": "32 km WSW of Sarangani, Philippines",
          "time": "2026-07-14T15:49:39.282Z",
          "coordinates": [
            125.1801,
            5.3226,
            46.427
          ],
          "tsunami": false,
          "significance": 639
        },
        {
          "id": "ci41292687",
          "magnitude": 4.31762677888687,
          "place": "18 km WSW of Johannesburg, CA",
          "time": "2026-07-13T16:40:55.170Z",
          "coordinates": [
            -117.814833333333,
            35.3121666666667,
            7.55
          ],
          "tsunami": false,
          "significance": 667
        },
        {
          "id": "us7000t01n",
          "magnitude": 6.3,
          "place": "southeast of the Loyalty Islands",
          "time": "2026-07-13T14:45:49.203Z",
          "coordinates": [
            171.5199,
            -22.7889,
            10
          ],
          "tsunami": false,
          "significance": 611
        },
        {
          "id": "us7000szzy",
          "magnitude": 6.4,
          "place": "191 km SE of Lorengau, Papua New Guinea",
          "time": "2026-07-13T08:53:27.913Z",
          "coordinates": [
            148.5218,
            -3.2207,
            10
          ],
          "tsunami": false,
          "significance": 630
        },
        {
          "id": "ci41291863",
          "magnitude": 4.10922888670317,
          "place": "2 km ESE of Frazier Park, CA",
          "time": "2026-07-12T10:38:04.730Z",
          "coordinates": [
            -118.925833333333,
            34.8131666666667,
            13.09
          ],
          "tsunami": false,
          "significance": 641
        },
        {
          "id": "us7000szpb",
          "magnitude": 6.4,
          "place": "South Sandwich Islands region",
          "time": "2026-07-11T10:26:42.691Z",
          "coordinates": [
            -28.8526,
            -55.5424,
            26
          ],
          "tsunami": false,
          "significance": 630
        },
        {
          "id": "uw714040221",
          "magnitude": 3.8,
          "place": "2 km E of Oak Harbor, Washington",
          "time": "2026-07-02T06:35:47.600Z",
          "coordinates": [
            -122.6065,
            48.2888333333333,
            25.38
          ],
          "tsunami": false,
          "significance": 602
        },
        {
          "id": "us6000t9bg",
          "magnitude": 5.3,
          "place": "272 km SSE of Dunhuang, China",
          "time": "2026-06-30T23:44:54.898Z",
          "coordinates": [
            95.4116,
            37.7819,
            10
          ],
          "tsunami": false,
          "significance": 650
        },
        {
          "id": "aka2026mpitdk",
          "magnitude": 4.2,
          "place": "27 km WNW of Hope, Alaska",
          "time": "2026-06-27T05:25:52.321Z",
          "coordinates": [
            -150.125,
            60.989,
            47.9
          ],
          "tsunami": false,
          "significance": 674
        },
        {
          "id": "us6000t8ec",
          "magnitude": 6.5,
          "place": "44 km SW of Balangonan, Philippines",
          "time": "2026-06-26T11:34:41.463Z",
          "coordinates": [
            125.0719,
            5.2867,
            42
          ],
          "tsunami": false,
          "significance": 685
        },
        {
          "id": "us6000t7zq",
          "magnitude": 6.9,
          "place": "33 km ENE of Noda, Japan",
          "time": "2026-06-24T22:30:12.989Z",
          "coordinates": [
            142.1614,
            40.2515,
            34
          ],
          "tsunami": false,
          "significance": 798
        },
        {
          "id": "us6000t7zp",
          "magnitude": 7.5,
          "place": "20 km ESE of Yumare, Venezuela",
          "time": "2026-06-24T22:05:11.743Z",
          "coordinates": [
            -68.5036,
            10.5086,
            10
          ],
          "tsunami": false,
          "significance": 2686
        },
        {
          "id": "us6000t7zc",
          "magnitude": 7.2,
          "place": "21 km ENE of San Felipe, Venezuela",
          "time": "2026-06-24T22:04:34.363Z",
          "coordinates": [
            -68.5571,
            10.4085,
            27.588
          ],
          "tsunami": false,
          "significance": 2000
        },
        {
          "id": "nc75382936",
          "magnitude": 5.59,
          "place": "11 km N of Redwood Valley, CA",
          "time": "2026-06-24T15:10:40.760Z",
          "coordinates": [
            -123.228833333333,
            39.3623333333333,
            8.85
          ],
          "tsunami": false,
          "significance": 1330
        }
      ]
    },
    "hazards": {
      "totalActive": 50,
      "byCategory": {
        "Severe Storms": 3,
        "Wildfires": 46,
        "Sea and Lake Ice": 1
      },
      "events": [
        {
          "id": "EONET_21437",
          "title": "Tropical Storm Bertha",
          "categories": [
            "Severe Storms"
          ],
          "sources": [
            "JTWC",
            "NOAA_NHC"
          ],
          "geometry": {
            "magnitudeValue": 35,
            "magnitudeUnit": "kts",
            "date": "2026-07-21T00:00:00Z",
            "type": "Point",
            "coordinates": [
              -86,
              28.5
            ]
          }
        },
        {
          "id": "EONET_21403",
          "title": "Wildfire Big Gulch, Moffat, Colorado",
          "categories": [
            "Wildfires"
          ],
          "sources": [
            "IRWIN"
          ],
          "geometry": {
            "magnitudeValue": 1600,
            "magnitudeUnit": "acres",
            "date": "2026-07-19T21:36:00Z",
            "type": "Point",
            "coordinates": [
              -107.671833,
              40.681667
            ]
          }
        },
        {
          "id": "EONET_21399",
          "title": "Hurricane Fausto",
          "categories": [
            "Severe Storms"
          ],
          "sources": [
            "JTWC"
          ],
          "geometry": {
            "magnitudeValue": 75,
            "magnitudeUnit": "kts",
            "date": "2026-07-22T06:00:00Z",
            "type": "Point",
            "coordinates": [
              -120.4,
              16.6
            ]
          }
        },
        {
          "id": "EONET_21421",
          "title": "Wildfire BROOK, Shasta, California",
          "categories": [
            "Wildfires"
          ],
          "sources": [
            "IRWIN"
          ],
          "geometry": {
            "magnitudeValue": 502,
            "magnitudeUnit": "acres",
            "date": "2026-07-18T19:12:00Z",
            "type": "Point",
            "coordinates": [
              -122.197625,
              40.698456
            ]
          }
        },
        {
          "id": "EONET_21404",
          "title": "Wildfire Horse Island, Berkeley, South Carolina",
          "categories": [
            "Wildfires"
          ],
          "sources": [
            "IRWIN"
          ],
          "geometry": {
            "magnitudeValue": 550,
            "magnitudeUnit": "acres",
            "date": "2026-07-18T17:43:00Z",
            "type": "Point",
            "coordinates": [
              -79.662533,
              33.188917
            ]
          }
        },
        {
          "id": "EONET_21402",
          "title": "Wildfire Ohio, Blaine, Idaho",
          "categories": [
            "Wildfires"
          ],
          "sources": [
            "IRWIN"
          ],
          "geometry": {
            "magnitudeValue": 2000,
            "magnitudeUnit": "acres",
            "date": "2026-07-18T15:52:00Z",
            "type": "Point",
            "coordinates": [
              -114.31795,
              43.588417
            ]
          }
        },
        {
          "id": "EONET_21420",
          "title": "Wildfire BISCAR, Lassen, California",
          "categories": [
            "Wildfires"
          ],
          "sources": [
            "IRWIN"
          ],
          "geometry": {
            "magnitudeValue": 12338,
            "magnitudeUnit": "acres",
            "date": "2026-07-18T14:11:00Z",
            "type": "Point",
            "coordinates": [
              -120.303833,
              40.618167
            ]
          }
        },
        {
          "id": "EONET_21416",
          "title": "Wildfire 0512 BOX SPRINGS, Jefferson, Oregon",
          "categories": [
            "Wildfires"
          ],
          "sources": [
            "IRWIN"
          ],
          "geometry": {
            "magnitudeValue": 4000,
            "magnitudeUnit": "acres",
            "date": "2026-07-17T21:13:00Z",
            "type": "Point",
            "coordinates": [
              -120.4985,
              44.635333
            ]
          }
        },
        {
          "id": "EONET_21433",
          "title": "Wildfire WALLACE WALKER, Franklin, Washington",
          "categories": [
            "Wildfires"
          ],
          "sources": [
            "IRWIN"
          ],
          "geometry": {
            "magnitudeValue": 798,
            "magnitudeUnit": "acres",
            "date": "2026-07-17T19:33:00Z",
            "type": "Point",
            "coordinates": [
              -118.567968,
              46.576482
            ]
          }
        },
        {
          "id": "EONET_21426",
          "title": "Wildfire DEVIL&#039;S CANYON, Franklin, Washington",
          "categories": [
            "Wildfires"
          ],
          "sources": [
            "IRWIN"
          ],
          "geometry": {
            "magnitudeValue": 4747,
            "magnitudeUnit": "acres",
            "date": "2026-07-17T19:31:00Z",
            "type": "Point",
            "coordinates": [
              -118.548791,
              46.600003
            ]
          }
        },
        {
          "id": "EONET_21415",
          "title": "Wildfire BERGER (50), Palm Beach, Florida",
          "categories": [
            "Wildfires"
          ],
          "sources": [
            "IRWIN"
          ],
          "geometry": {
            "magnitudeValue": 11200,
            "magnitudeUnit": "acres",
            "date": "2026-07-17T19:18:00Z",
            "type": "Point",
            "coordinates": [
              -80.8444444,
              26.4466667
            ]
          }
        },
        {
          "id": "EONET_21410",
          "title": "Incident Complex HAY CREEK COMPLEX, Gilliam, Oregon",
          "categories": [
            "Wildfires"
          ],
          "sources": [
            "IRWIN"
          ],
          "geometry": {
            "magnitudeValue": 92211,
            "magnitudeUnit": "acres",
            "date": "2026-07-17T17:16:00Z",
            "type": "Point",
            "coordinates": [
              -120.435846,
              45.26602
            ]
          }
        },
        {
          "id": "EONET_21425",
          "title": "Wildfire NEFF JONES, Franklin, Washington",
          "categories": [
            "Wildfires"
          ],
          "sources": [
            "IRWIN"
          ],
          "geometry": {
            "magnitudeValue": 7123,
            "magnitudeUnit": "acres",
            "date": "2026-07-17T14:34:00Z",
            "type": "Point",
            "coordinates": [
              -118.65817,
              46.45851
            ]
          }
        },
        {
          "id": "EONET_21427",
          "title": "Wildfire Modrite, Ferry, Washington",
          "categories": [
            "Wildfires"
          ],
          "sources": [
            "IRWIN"
          ],
          "geometry": {
            "magnitudeValue": 5679,
            "magnitudeUnit": "acres",
            "date": "2026-07-17T13:59:00Z",
            "type": "Point",
            "coordinates": [
              -118.312583,
              48.069
            ]
          }
        },
        {
          "id": "EONET_21412",
          "title": "Wildfire POWDER RIVER, Baker, Oregon",
          "categories": [
            "Wildfires"
          ],
          "sources": [
            "IRWIN"
          ],
          "geometry": {
            "magnitudeValue": 18345,
            "magnitudeUnit": "acres",
            "date": "2026-07-17T07:27:00Z",
            "type": "Point",
            "coordinates": [
              -117.277667,
              44.75525
            ]
          }
        },
        {
          "id": "EONET_21408",
          "title": "Wildfire 0462, Sherman, Oregon",
          "categories": [
            "Wildfires"
          ],
          "sources": [
            "IRWIN"
          ],
          "geometry": {
            "magnitudeValue": 11581,
            "magnitudeUnit": "acres",
            "date": "2026-07-17T00:37:00Z",
            "type": "Point",
            "coordinates": [
              -120.495333,
              45.184333
            ]
          }
        },
        {
          "id": "EONET_12618",
          "title": "Iceberg A84",
          "categories": [
            "Sea and Lake Ice"
          ],
          "sources": [
            "NATICE"
          ],
          "geometry": {
            "magnitudeValue": 72,
            "magnitudeUnit": "NM^2",
            "date": "2026-07-17T00:00:00Z",
            "type": "Point",
            "coordinates": [
              -107.7,
              -72.02
            ]
          }
        },
        {
          "id": "EONET_21422",
          "title": "Wildfire COLUMBIA COUNTY, Columbia, Washington",
          "categories": [
            "Wildfires"
          ],
          "sources": [
            "IRWIN"
          ],
          "geometry": {
            "magnitudeValue": 750,
            "magnitudeUnit": "acres",
            "date": "2026-07-16T22:12:00Z",
            "type": "Point",
            "coordinates": [
              -118.103667,
              46.542667
            ]
          }
        },
        {
          "id": "EONET_21401",
          "title": "Wildfire 0497 HENRY, Crook, Oregon",
          "categories": [
            "Wildfires"
          ],
          "sources": [
            "IRWIN"
          ],
          "geometry": {
            "magnitudeValue": 25000,
            "magnitudeUnit": "acres",
            "date": "2026-07-16T21:22:00Z",
            "type": "Point",
            "coordinates": [
              -119.947717,
              44.121117
            ]
          }
        },
        {
          "id": "EONET_21406",
          "title": "Wildfire Hagen, Umatilla, Oregon",
          "categories": [
            "Wildfires"
          ],
          "sources": [
            "IRWIN"
          ],
          "geometry": {
            "magnitudeValue": 700,
            "magnitudeUnit": "acres",
            "date": "2026-07-16T21:04:00Z",
            "type": "Point",
            "coordinates": [
              -118.269,
              45.707
            ]
          }
        },
        {
          "id": "EONET_21400",
          "title": "Wildfire 0500 COYOTE, Crook, Oregon",
          "categories": [
            "Wildfires"
          ],
          "sources": [
            "IRWIN"
          ],
          "geometry": {
            "magnitudeValue": 15000,
            "magnitudeUnit": "acres",
            "date": "2026-07-16T20:39:00Z",
            "type": "Point",
            "coordinates": [
              -120.528667,
              44.1115
            ]
          }
        },
        {
          "id": "EONET_21405",
          "title": "Wildfire Egypt, Harney, Oregon",
          "categories": [
            "Wildfires"
          ],
          "sources": [
            "IRWIN"
          ],
          "geometry": {
            "magnitudeValue": 4685,
            "magnitudeUnit": "acres",
            "date": "2026-07-16T20:11:00Z",
            "type": "Point",
            "coordinates": [
              -119.468417,
              43.727167
            ]
          }
        },
        {
          "id": "EONET_21407",
          "title": "Wildfire 0476 HOAG, Gilliam, Oregon",
          "categories": [
            "Wildfires"
          ],
          "sources": [
            "IRWIN"
          ],
          "geometry": {
            "magnitudeValue": 50403,
            "magnitudeUnit": "acres",
            "date": "2026-07-16T20:08:00Z",
            "type": "Point",
            "coordinates": [
              -120.405117,
              45.562183
            ]
          }
        },
        {
          "id": "EONET_21418",
          "title": "Wildfire 0485 DEEP CANYON, Wasco, Oregon",
          "categories": [
            "Wildfires"
          ],
          "sources": [
            "IRWIN"
          ],
          "geometry": {
            "magnitudeValue": 8062,
            "magnitudeUnit": "acres",
            "date": "2026-07-16T20:08:00Z",
            "type": "Point",
            "coordinates": [
              -120.836,
              44.8645
            ]
          }
        },
        {
          "id": "EONET_21413",
          "title": "Wildfire 0494 AKAWA BUTTE, Jefferson, Oregon",
          "categories": [
            "Wildfires"
          ],
          "sources": [
            "IRWIN"
          ],
          "geometry": {
            "magnitudeValue": 6856,
            "magnitudeUnit": "acres",
            "date": "2026-07-16T18:18:00Z",
            "type": "Point",
            "coordinates": [
              -121.453167,
              44.472367
            ]
          }
        },
        {
          "id": "EONET_21411",
          "title": "Wildfire Bologna, Grant, Oregon",
          "categories": [
            "Wildfires"
          ],
          "sources": [
            "IRWIN"
          ],
          "geometry": {
            "magnitudeValue": 2600,
            "magnitudeUnit": "acres",
            "date": "2026-07-16T17:52:00Z",
            "type": "Point",
            "coordinates": [
              -119.598,
              44.861167
            ]
          }
        },
        {
          "id": "EONET_21432",
          "title": "Wildfire Mile Marker 40- Broward (06), Broward, Florida",
          "categories": [
            "Wildfires"
          ],
          "sources": [
            "IRWIN"
          ],
          "geometry": {
            "magnitudeValue": 6750,
            "magnitudeUnit": "acres",
            "date": "2026-07-16T16:36:00Z",
            "type": "Point",
            "coordinates": [
              -80.5405556,
              26.2566667
            ]
          }
        },
        {
          "id": "EONET_21409",
          "title": "Wildfire 0480 WILCOX, Sherman, Oregon",
          "categories": [
            "Wildfires"
          ],
          "sources": [
            "IRWIN"
          ],
          "geometry": {
            "magnitudeValue": 4112,
            "magnitudeUnit": "acres",
            "date": "2026-07-16T16:25:00Z",
            "type": "Point",
            "coordinates": [
              -120.6097,
              45.113583
            ]
          }
        },
        {
          "id": "EONET_21419",
          "title": "Incident Complex ROWE CREEK COMPLEX, Wheeler, Oregon",
          "categories": [
            "Wildfires"
          ],
          "sources": [
            "IRWIN"
          ],
          "geometry": {
            "magnitudeValue": 126009,
            "magnitudeUnit": "acres",
            "date": "2026-07-16T16:20:00Z",
            "type": "Point",
            "coordinates": [
              -120.316732,
              44.810126
            ]
          }
        },
        {
          "id": "EONET_21428",
          "title": "Wildfire ROYAL LAKE, Adams, Washington",
          "categories": [
            "Wildfires"
          ],
          "sources": [
            "IRWIN"
          ],
          "geometry": {
            "magnitudeValue": 2037,
            "magnitudeUnit": "acres",
            "date": "2026-07-16T13:55:00Z",
            "type": "Point",
            "coordinates": [
              -119.361131,
              46.863295
            ]
          }
        }
      ]
    },
    "atmospheric": {
      "referencePoints": [
        {
          "name": "Arctic",
          "lat": 80,
          "lon": 0,
          "temperature_2m": -0.1,
          "surface_pressure": 1005.8,
          "wind_speed_10m": 6.61,
          "relative_humidity_2m": 94
        },
        {
          "name": "North Atlantic",
          "lat": 50,
          "lon": -30,
          "temperature_2m": 16.4,
          "surface_pressure": 1033.7,
          "wind_speed_10m": 5.79,
          "relative_humidity_2m": 87
        },
        {
          "name": "Tropics West",
          "lat": 5,
          "lon": -60,
          "temperature_2m": 24.4,
          "surface_pressure": 915.8,
          "wind_speed_10m": 2.66,
          "relative_humidity_2m": 64
        },
        {
          "name": "Tropics East",
          "lat": 5,
          "lon": 100,
          "temperature_2m": 30.1,
          "surface_pressure": 1011.9,
          "wind_speed_10m": 1.01,
          "relative_humidity_2m": 65
        },
        {
          "name": "Southern Ocean",
          "lat": -55,
          "lon": 0,
          "temperature_2m": -5.1,
          "surface_pressure": 985.5,
          "wind_speed_10m": 14.47,
          "relative_humidity_2m": 59
        },
        {
          "name": "Antarctic",
          "lat": -80,
          "lon": 0,
          "temperature_2m": -44,
          "surface_pressure": 718,
          "wind_speed_10m": 11.15,
          "relative_humidity_2m": 52
        }
      ]
    },
    "climate": {
      "error": "[NOAA Climate (keyless)] Unexpected token '<', \"<!DOCTYPE \"... is not valid JSON"
    },
    "oceanHeat": {
      "error": "[NOAA CRW Ocean Heat] HTTP 404 Not Found"
    },
    "cryosphere": {
      "error": "[NSIDC Sea Ice] HTTP 404 Not Found"
    }
  }
}